pysauron/__init__.py
pysauron/datasets/__init__.py
pysauron/datasets/avenue.py
pysauron/datasets/shanghaitech.py
pysauron/datasets/ucf_crime.py
pysauron/datasets/xd_violence.py
pysauron/transforms/__init__.py
pysauron/transforms/transforms.py
pysauron-0.0.3.dist-info/LICENSE
pysauron-0.0.3.dist-info/METADATA
pysauron-0.0.3.dist-info/WHEEL
pysauron-0.0.3.dist-info/top_level.txt
pysauron-0.0.3.dist-info/RECORD
