Metadata-Version: 2.1
Name: pysauron
Version: 0.0.3
Summary: A collection of datasets for video anomaly detection
Home-page: https://github.com/KyloRen1/PySauron
Author: Bogdan Ivanyuk-Skulskyi
Author-email: Bogdan Ivanyuk-Skulskyi <ivanyuk.bogdan1999@gmail.com>
License: MIT License
Project-URL: repository, https://github.com/KyloRen1/PySauron
Keywords: anomaly-detection
Classifier: Intended Audience :: Developers
Classifier: Intended Audience :: Education
Classifier: Intended Audience :: Science/Research
Classifier: License :: OSI Approved :: MIT License
Classifier: Programming Language :: Python :: 3
Classifier: Programming Language :: Python :: 3.8
Requires-Python: >=3.8.0
License-File: LICENSE
Requires-Dist: scipy ==1.11.4
Requires-Dist: Pillow ==10.1.0
Requires-Dist: torch ==2.1.0
Requires-Dist: torchvision ==0.16.0
Requires-Dist: numpy ==1.26.4
Requires-Dist: av ==10.0.0
